pypax/__init__.py
pypax/pax_action.py
pypax/pax_action_modify_helm_image.py
pypax/pax_action_update_node.py
pypax/pax_actions.yml
pypax/pax_deploy.py
pypax/pax_global.py
pypax/pax_initialize.py
pypax/pypax.py
pypax-0.0.73.data/scripts/pax
pypax-0.0.73.dist-info/METADATA
pypax-0.0.73.dist-info/WHEEL
pypax-0.0.73.dist-info/top_level.txt
pypax-0.0.73.dist-info/RECORD
